pyramid_prometheus
