Metadata-Version: 1.1
Name: pyramid-prometheus
Version: 0.6
Summary: Pyramid Integration for Prometheus
